suds/__init__.py
suds/builder.py
suds/cache.py
suds/client.py
suds/compat.py
suds/metrics.py
suds/options.py
suds/plugin.py
suds/properties.py
suds/reader.py
suds/resolver.py
suds/servicedefinition.py
suds/serviceproxy.py
suds/soaparray.py
suds/store.py
suds/sudsobject.py
suds/utils.py
suds/wsdl.py
suds/wsse.py
suds/__pycache__/__init__.cpython-34.pyo
suds/__pycache__/builder.cpython-34.pyo
suds/__pycache__/cache.cpython-34.pyo
suds/__pycache__/client.cpython-34.pyo
suds/__pycache__/compat.cpython-34.pyo
suds/__pycache__/metrics.cpython-34.pyo
suds/__pycache__/options.cpython-34.pyo
suds/__pycache__/plugin.cpython-34.pyo
suds/__pycache__/properties.cpython-34.pyo
suds/__pycache__/reader.cpython-34.pyo
suds/__pycache__/resolver.cpython-34.pyo
suds/__pycache__/servicedefinition.cpython-34.pyo
suds/__pycache__/serviceproxy.cpython-34.pyo
suds/__pycache__/soaparray.cpython-34.pyo
suds/__pycache__/store.cpython-34.pyo
suds/__pycache__/sudsobject.cpython-34.pyo
suds/__pycache__/utils.cpython-34.pyo
suds/__pycache__/wsdl.cpython-34.pyo
suds/__pycache__/wsse.cpython-34.pyo
suds/bindings/__init__.py
suds/bindings/binding.py
suds/bindings/document.py
suds/bindings/multiref.py
suds/bindings/rpc.py
suds/bindings/__pycache__/__init__.cpython-34.pyo
suds/bindings/__pycache__/binding.cpython-34.pyo
suds/bindings/__pycache__/document.cpython-34.pyo
suds/bindings/__pycache__/multiref.cpython-34.pyo
suds/bindings/__pycache__/rpc.cpython-34.pyo
suds/mx/__init__.py
suds/mx/appender.py
suds/mx/basic.py
suds/mx/core.py
suds/mx/encoded.py
suds/mx/literal.py
suds/mx/typer.py
suds/mx/__pycache__/__init__.cpython-34.pyo
suds/mx/__pycache__/appender.cpython-34.pyo
suds/mx/__pycache__/basic.cpython-34.pyo
suds/mx/__pycache__/core.cpython-34.pyo
suds/mx/__pycache__/encoded.cpython-34.pyo
suds/mx/__pycache__/literal.cpython-34.pyo
suds/mx/__pycache__/typer.cpython-34.pyo
suds/sax/__init__.py
suds/sax/attribute.py
suds/sax/date.py
suds_py3_fixes-1.2.0.2.dist-info/DESCRIPTION.rst
suds_py3_fixes-1.2.0.2.dist-info/METADATA
suds_py3_fixes-1.2.0.2.dist-info/RECORD
suds_py3_fixes-1.2.0.2.dist-info/WHEEL
suds_py3_fixes-1.2.0.2.dist-info/metadata.json
suds_py3_fixes-1.2.0.2.dist-info/top_level.txt
