Metadata-Version: 2.0
Name: suds-py3-fixes
Version: 1.2.0.2
Summary: Lightweight SOAP client
Home-page: https://github.com/andreif/suds-py3
Author: Cackharot (original Jeff Ortel)
Author-email: cackharot@gmail.com
License: LGPL
Keywords: soap,wsdl,basic http binding,basic auth
Platform: Python3
Classifier: Programming Language :: Python
Classifier: Programming Language :: Python :: 3
Classifier: Intended Audience :: Developers
Classifier: License :: OSI Approved :: GNU Library or Lesser General Public License (LGPL)
Classifier: Operating System :: OS Independent
